pycartociudad/__init__.py
pycartociudad/geocode.py
pycartociudad/get_location_info.py
pycartociudad/pycartociudad.py
pycartociudad/reverse_geocode.py
pycartociudad/route_between_two_points.py
pycartociudad-0.1.0.dist-info/LICENSE
pycartociudad-0.1.0.dist-info/METADATA
pycartociudad-0.1.0.dist-info/WHEEL
pycartociudad-0.1.0.dist-info/top_level.txt
pycartociudad-0.1.0.dist-info/RECORD
