Metadata-Version: 2.1
Name: pycartociudad
Version: 0.1.0
Summary: PyCartociudad contains Python functions to access the CartoCiudad REST and WPS API (REST y WPS) from IGN with spanish cartography services.
Home-page: https://github.com/pyladiesmadrid/pycartociudad
Author: PyLadies Madrid
Author-email: madrid@pyladies.com
License: GPLv3+
Keywords: pycartociudad
Platform: UNKNOWN
Classifier: Development Status :: 2 - Pre-Alpha
Classifier: Intended Audience :: Developers
Classifier: License :: OSI Approved :: GNU General Public License v3 or later (GPLv3+)
Classifier: Natural Language :: English
Classifier: Programming Language :: Python :: 3
Classifier: Programming Language :: Python :: 3.5
Classifier: Programming Language :: Python :: 3.6
Classifier: Programming Language :: Python :: 3.7
Classifier: Programming Language :: Python :: 3.8
Requires-Python: >=3.5
Requires-Dist: requests
